pipeliner/__init__.py
pipeliner/examples/__init__.py
pipeliner/examples/process_image/__init__.py
pipeliner/examples/process_image/processors.py
pipeliner/examples/process_image/readers.py
pipeliner/examples/process_text_file/__init__.py
pipeliner/examples/process_text_file/processors.py
pipeliner/processors/__init__.py
pipeliner/processors/base.py
pipeliner/readers/__init__.py
pipeliner/readers/base.py
pipeliner/readers/bulk_readers.py
pipeliner/readers/stream_readers.py
pipeliner/runners/__init__.py
pipeliner/runners/base.py
pipeliner/utils/__init__.py
pipeliner/utils/csv_utils.py
pipeliner/utils/decorators.py
pipeliner/utils/string_utils.py
simple_pipeliner-0.0.3.dist-info/LICENSE
simple_pipeliner-0.0.3.dist-info/METADATA
simple_pipeliner-0.0.3.dist-info/WHEEL
simple_pipeliner-0.0.3.dist-info/top_level.txt
simple_pipeliner-0.0.3.dist-info/RECORD
